{"cameraMode":{"drawMode":0,"name":"Shaded","section":"Shading Mode"},"sceneLighting":false,"audioPlay":false,"sceneViewState":{"showFog":true,"showMaterialUpdate":false,"showSkybox":false,"showFlares":true,"showImageEffects":true,"showParticleSystems":true},"in2DMode":false,"pivot":{"x":-0.05799427628517151,"y":0.4368322491645813,"z":0.0},"rotation":{"x":-0.03308749943971634,"y":-0.9470095038414002,"z":0.30262672901153567,"w":-0.10344760864973068},"size":0.9867174029350281,"orthographic":false}